skadi/__init__.py
skadi/cli.py
skadi/skadi.py
skadi-0.1.0.dist-info/AUTHORS.rst
skadi-0.1.0.dist-info/LICENSE
skadi-0.1.0.dist-info/METADATA
skadi-0.1.0.dist-info/WHEEL
skadi-0.1.0.dist-info/entry_points.txt
skadi-0.1.0.dist-info/top_level.txt
skadi-0.1.0.dist-info/RECORD
